{
  "notes": [
    {
      "title": "Dolores qui ullam mo",
      "details": "Amet et eos et ut ",
      "skill": "JavaScript",
      "id": 1
    },
    {
      "title": "Ut ea commodo volupt",
      "details": "Iste voluptatibus ma",
      "skill": "JavaScript",
      "id": 9
    },
    {
      "title": "Et blanditiis in in ",
      "details": "Aliquam facere est ",
      "skill": "Node JS",
      "id": 12
    },
    {
      "title": "Ut commodo reiciendi",
      "details": "Do voluptatem proide",
      "skill": "JavaScript",
      "id": 13
    },
    {
      "title": "Commodi consequatur",
      "details": "Molestias assumenda ",
      "skill": "React JS",
      "id": 14
    },
    {
      "title": "Soluta similique nih",
      "details": "Dolorem autem iusto ",
      "skill": "Java",
      "id": 15
    }
  ]
}